mp4analyser/__init__.py
mp4analyser/core.py
mp4analyser/iso.py
mp4analyser/non_iso.py
mp4analyser/summary.py
mp4analyser/util.py
mp4analyser-0.0.1.dist-info/LICENSE
mp4analyser-0.0.1.dist-info/METADATA
mp4analyser-0.0.1.dist-info/WHEEL
mp4analyser-0.0.1.dist-info/top_level.txt
mp4analyser-0.0.1.dist-info/RECORD
