Metadata-Version: 2.1
Name: mp4analyser
Version: 0.0.1
Summary: PyPI mirror for essential61/mp4analyser
Home-page: https://github.com/xziyue/mp4analyser
Author: Ziyue "Alan" Xiang
Author-email: ziyue.alan.xiang@gmail.com
License: UNKNOWN
Platform: UNKNOWN
Classifier: Programming Language :: Python :: 3
Classifier: License :: OSI Approved :: GNU Lesser General Public License v3 (LGPLv3)
Classifier: Operating System :: OS Independent
Requires-Python: >=3.8
